{
  "sections": {
    "introduction_hero": {
      "type": "custom-introduction-hero",
      "settings": {}
    },
    "fullscreen_banner_1": {
      "type": "custom-fullscreen-banner-1",
      "settings": {}
    },
    "gallery_block_1": {
      "type": "custom-gallery-block-1",
      "settings": {}
    },
    "fullscreen_banner_2": {
      "type": "custom-fullscreen-banner-2",
      "settings": {}
    },
    "gallery_block_2": {
      "type": "custom-gallery-block-2",
      "settings": {}
    },
    "gallery_block_3": {
      "type": "custom-gallery-block-3",
      "settings": {}
    },
    "fullscreen_banner_3": {
      "type": "custom-fullscreen-banner-3",
      "settings": {}
    }
  },
  "order": [
    "introduction_hero",
    "fullscreen_banner_1",
    "gallery_block_1",
    "fullscreen_banner_2",
    "gallery_block_2",
    "gallery_block_3",
    "fullscreen_banner_3"
  ]
}
